{
  "__type__": "cc.Mesh",
  "_name": "",
  "_objFlags": 0,
  "_native": ".bin",
  "_struct": {
    "primitives": [
      {
        "primitiveMode": 7,
        "vertexBundelIndices": [
          0
        ],
        "indexView": {
          "offset": 44576,
          "length": 7992,
          "count": 1998,
          "stride": 4
        }
      }
    ],
    "vertexBundles": [
      {
        "view": {
          "offset": 0,
          "length": 44576,
          "count": 796,
          "stride": 56
        },
        "attributes": [
          {
            "name": "a_position",
            "format": 32,
            "isNormalized": false
          },
          {
            "name": "a_normal",
            "format": 32,
            "isNormalized": false
          },
          {
            "name": "a_texCoord",
            "format": 21,
            "isNormalized": false
          },
          {
            "name": "a_tangent",
            "format": 44,
            "isNormalized": false
          },
          {
            "name": "a_texCoord1",
            "format": 21,
            "isNormalized": false
          }
        ]
      }
    ],
    "minPosition": {
      "__type__": "cc.Vec3",
      "x": -0.1684497594833374,
      "y": -0.00014462470426224172,
      "z": -0.17125588655471802
    },
    "maxPosition": {
      "__type__": "cc.Vec3",
      "x": 0.15730515122413635,
      "y": 0.2806728780269623,
      "z": 0.1712634414434433
    }
  },
  "_hash": 3888213481
}