[
    1,
    0,
    0,
    [
        [
            "cc.Mesh",
            [
                "_native",
                "_hash",
                "_struct"
            ],
            1,
            11
        ]
    ],
    [
        [
            0,
            0,
            1,
            2,
            3
        ]
    ],
    [
        [
            0,
            ".bin",
            3180502622,
            [
                {
                    "primitives": [
                        {
                            "primitiveMode": 7,
                            "vertexBundelIndices": [
                                0
                            ],
                            "indexView": {
                                "offset": 6768,
                                "length": 2220,
                                "count": 555,
                                "stride": 4
                            }
                        }
                    ],
                    "vertexBundles": [
                        {
                            "view": {
                                "offset": 0,
                                "length": 6768,
                                "count": 141,
                                "stride": 48
                            },
                            "attributes": [
                                {
                                    "name": "a_position",
                                    "format": 32,
                                    "isNormalized": false
                                },
                                {
                                    "name": "a_normal",
                                    "format": 32,
                                    "isNormalized": false
                                },
                                {
                                    "name": "a_texCoord",
                                    "format": 21,
                                    "isNormalized": false
                                },
                                {
                                    "name": "a_tangent",
                                    "format": 44,
                                    "isNormalized": false
                                }
                            ]
                        }
                    ]
                },
                "minPosition",
                8,
                [
                    1,
                    -0.047502223402261734,
                    0.0035762412007898092,
                    -0.3872179687023163
                ],
                "maxPosition",
                8,
                [
                    1,
                    0.9118801951408386,
                    1.7248553037643433,
                    0.22327345609664917
                ]
            ]
        ],
        -1
    ],
    0,
    0,
    [],
    [],
    []
]
