{
  "__type__": "cc.Mesh",
  "_name": "",
  "_objFlags": 0,
  "_native": ".bin",
  "_struct": {
    "primitives": [
      {
        "primitiveMode": 7,
        "vertexBundelIndices": [
          0
        ],
        "indexView": {
          "offset": 18432,
          "length": 2304,
          "count": 576,
          "stride": 4
        }
      }
    ],
    "vertexBundles": [
      {
        "view": {
          "offset": 0,
          "length": 18432,
          "count": 384,
          "stride": 48
        },
        "attributes": [
          {
            "name": "a_position",
            "format": 32,
            "isNormalized": false
          },
          {
            "name": "a_normal",
            "format": 32,
            "isNormalized": false
          },
          {
            "name": "a_texCoord",
            "format": 21,
            "isNormalized": false
          },
          {
            "name": "a_tangent",
            "format": 44,
            "isNormalized": false
          }
        ]
      }
    ],
    "minPosition": {
      "__type__": "cc.Vec3",
      "x": -52.0101318359375,
      "y": -59.195404052734375,
      "z": -36.698081970214844
    },
    "maxPosition": {
      "__type__": "cc.Vec3",
      "x": 52.01020812988281,
      "y": 59.19575500488281,
      "z": 36.6981201171875
    }
  },
  "_hash": 1161380406
}