[
    1,
    0,
    0,
    [
        [
            "cc.Mesh",
            [
                "_native",
                "_hash",
                "_struct"
            ],
            1,
            11
        ]
    ],
    [
        [
            0,
            0,
            1,
            2,
            3
        ]
    ],
    [
        [
            0,
            ".bin",
            3729151465,
            [
                {
                    "primitives": [
                        {
                            "primitiveMode": 7,
                            "vertexBundelIndices": [
                                0
                            ],
                            "indexView": {
                                "offset": 5664,
                                "length": 2352,
                                "count": 588,
                                "stride": 4
                            }
                        }
                    ],
                    "vertexBundles": [
                        {
                            "view": {
                                "offset": 0,
                                "length": 5664,
                                "count": 118,
                                "stride": 48
                            },
                            "attributes": [
                                {
                                    "name": "a_position",
                                    "format": 32,
                                    "isNormalized": false
                                },
                                {
                                    "name": "a_normal",
                                    "format": 32,
                                    "isNormalized": false
                                },
                                {
                                    "name": "a_texCoord",
                                    "format": 21,
                                    "isNormalized": false
                                },
                                {
                                    "name": "a_tangent",
                                    "format": 44,
                                    "isNormalized": false
                                }
                            ]
                        }
                    ]
                },
                "minPosition",
                8,
                [
                    1,
                    -0.05389640852808952,
                    -0.3766932189464569,
                    -0.3195401132106781
                ],
                "maxPosition",
                8,
                [
                    1,
                    0.053893543779850006,
                    0.3766932189464569,
                    0.3195400834083557
                ]
            ]
        ],
        -1
    ],
    0,
    0,
    [],
    [],
    []
]
