{
  "version": "2.1.10",
  "sourceTimeStamp": 1651070002511.4841,
  "outputTimeStamps": {
    "Books 2.jpg": 1651070002914.766,
    "Manmade04Diffuse.jpg": 1651070002907.799,
    "Manmade02Diffuse.jpg": 1651070002905.7478,
    "SE_Basket_01_Diffuse.jpg": 1651070002912.7476,
    "log.json": 1651070002919.7695,
    "out.bin": 1651070002916.0742,
    "out.gltf": 1651070002919.4766,
    "tekstura domina 1.png": 1651070002904.5818,
    "tekstura domina 2.png": 1651070002904.1665,
    "tekstura domina 3.png": 1651070002904.8254,
    "tekstura domina 4.png": 1651070002910.8577,
    "tekstura domina 5.png": 1651070002911.295,
    "tekstura domina 6.png": 1651070002911.0732,
    "tekstura domina 7.png": 1651070002909.8855,
    ".fbm/BD2027EC/Goldberg 1 27. april.fbm/Books 2.jpg": 1651070002871.4705,
    ".fbm/BD2027EC/Goldberg 1 27. april.fbm/Manmade02Diffuse.jpg": 1651070002869.6404,
    ".fbm/BD2027EC/Goldberg 1 27. april.fbm/Manmade04Diffuse.jpg": 1651070002870.0679,
    ".fbm/BD2027EC/Goldberg 1 27. april.fbm/SE_Basket_01_Diffuse.jpg": 1651070002871.1963,
    ".fbm/BD2027EC/Goldberg 1 27. april.fbm/tekstura domina 1.png": 1651070002869.0886,
    ".fbm/BD2027EC/Goldberg 1 27. april.fbm/tekstura domina 2.png": 1651070002868.903,
    ".fbm/BD2027EC/Goldberg 1 27. april.fbm/tekstura domina 3.png": 1651070002869.229,
    ".fbm/BD2027EC/Goldberg 1 27. april.fbm/tekstura domina 5.png": 1651070002870.8628,
    ".fbm/BD2027EC/Goldberg 1 27. april.fbm/tekstura domina 4.png": 1651070002870.4368,
    ".fbm/BD2027EC/Goldberg 1 27. april.fbm/tekstura domina 6.png": 1651070002870.6167,
    ".fbm/BD2027EC/Goldberg 1 27. april.fbm/tekstura domina 7.png": 1651070002870.2273
  },
  "options": {}
}
