{
  "__type__": "cc.Mesh",
  "_name": "",
  "_objFlags": 0,
  "_native": ".bin",
  "_struct": {
    "primitives": [
      {
        "primitiveMode": 7,
        "vertexBundelIndices": [
          0
        ],
        "indexView": {
          "offset": 48664,
          "length": 8436,
          "count": 2109,
          "stride": 4
        }
      }
    ],
    "vertexBundles": [
      {
        "view": {
          "offset": 0,
          "length": 48664,
          "count": 869,
          "stride": 56
        },
        "attributes": [
          {
            "name": "a_position",
            "format": 32,
            "isNormalized": false
          },
          {
            "name": "a_normal",
            "format": 32,
            "isNormalized": false
          },
          {
            "name": "a_texCoord",
            "format": 21,
            "isNormalized": false
          },
          {
            "name": "a_tangent",
            "format": 44,
            "isNormalized": false
          },
          {
            "name": "a_texCoord1",
            "format": 21,
            "isNormalized": false
          }
        ]
      }
    ],
    "minPosition": {
      "__type__": "cc.Vec3",
      "x": -0.7817458510398865,
      "y": 0.00020176515681669116,
      "z": -0.7862041592597961
    },
    "maxPosition": {
      "__type__": "cc.Vec3",
      "x": 0.7809751629829407,
      "y": 1.3195152282714844,
      "z": 0.7812636494636536
    }
  },
  "_hash": 3721473677
}