[
    1,
    0,
    0,
    [
        [
            "cc.Mesh",
            [
                "_native",
                "_hash",
                "_struct"
            ],
            1,
            11
        ]
    ],
    [
        [
            0,
            0,
            1,
            2,
            3
        ]
    ],
    [
        [
            0,
            ".bin",
            1947293687,
            [
                {
                    "primitives": [
                        {
                            "primitiveMode": 7,
                            "vertexBundelIndices": [
                                0
                            ],
                            "indexView": {
                                "offset": 22848,
                                "length": 3648,
                                "count": 912,
                                "stride": 4
                            }
                        }
                    ],
                    "vertexBundles": [
                        {
                            "view": {
                                "offset": 0,
                                "length": 22848,
                                "count": 476,
                                "stride": 48
                            },
                            "attributes": [
                                {
                                    "name": "a_position",
                                    "format": 32,
                                    "isNormalized": false
                                },
                                {
                                    "name": "a_normal",
                                    "format": 32,
                                    "isNormalized": false
                                },
                                {
                                    "name": "a_texCoord",
                                    "format": 21,
                                    "isNormalized": false
                                },
                                {
                                    "name": "a_tangent",
                                    "format": 44,
                                    "isNormalized": false
                                }
                            ]
                        }
                    ]
                },
                "minPosition",
                8,
                [
                    1,
                    -0.2952825725078583,
                    -0.3975311815738678,
                    0.0009085368947125971
                ],
                "maxPosition",
                8,
                [
                    1,
                    0.294019877910614,
                    0.39753103256225586,
                    0.5817916393280029
                ]
            ]
        ],
        -1
    ],
    0,
    0,
    [],
    [],
    []
]
