{
  "__type__": "cc.Mesh",
  "_name": "",
  "_objFlags": 0,
  "_native": ".bin",
  "_struct": {
    "primitives": [
      {
        "primitiveMode": 7,
        "vertexBundelIndices": [
          0
        ],
        "indexView": {
          "offset": 12240,
          "length": 1560,
          "count": 390,
          "stride": 4
        }
      }
    ],
    "vertexBundles": [
      {
        "view": {
          "offset": 0,
          "length": 12240,
          "count": 255,
          "stride": 48
        },
        "attributes": [
          {
            "name": "a_position",
            "format": 32,
            "isNormalized": false
          },
          {
            "name": "a_normal",
            "format": 32,
            "isNormalized": false
          },
          {
            "name": "a_texCoord",
            "format": 21,
            "isNormalized": false
          },
          {
            "name": "a_tangent",
            "format": 44,
            "isNormalized": false
          }
        ]
      }
    ],
    "minPosition": {
      "__type__": "cc.Vec3",
      "x": -0.2268027812242508,
      "y": 0.01625925488770008,
      "z": -0.1430061310529709
    },
    "maxPosition": {
      "__type__": "cc.Vec3",
      "x": 4.961459636688232,
      "y": 2.374598741531372,
      "z": 0.19151349365711212
    }
  },
  "_hash": 4143151310
}